<?xml version="1.0"?>
<!DOCTYPE hibernate-mapping PUBLIC "-//Hibernate/Hibernate Mapping DTD 3.0//EN"
"http://www.hibernate.org/dtd/hibernate-mapping-3.0.dtd">
<!-- Generated Mar 18, 2018 10:53:53 AM by Hibernate Tools 4.3.1 -->
<hibernate-mapping>
    <class name="model.dataAccessLayer.entity.ItiStoreYCart" table="ITI_STORE_Y_CART" schema="STORE_Y" optimistic-lock="version">
        <id name="recid" type="big_decimal">
            <column name="RECID" precision="22" scale="0" />
            <generator class="assigned" />
        </id>
        <many-to-one name="itiStoreYUser" class="model.dataAccessLayer.entity.ItiStoreYUser" fetch="select">
            <column name="USERID" precision="22" scale="0" />
        </many-to-one>
        <property name="totalsum" type="big_decimal">
            <column name="TOTALSUM" precision="22" scale="0" />
        </property>
        <set name="itiStoreYProductcarts" table="ITI_STORE_Y_PRODUCTCART" inverse="true" lazy="true" fetch="select">
            <key>
                <column name="CARTID" precision="22" scale="0" />
            </key>
            <one-to-many class="model.dataAccessLayer.entity.ItiStoreYProductcart" />
        </set>
    </class>
</hibernate-mapping>
